pymod2pkg/__init__.py
pymod2pkg/cli/__init__.py
pymod2pkg/cli/pymod2pkg.py
pymod2pkg/cli/reqs2pkg.py
pymod2pkg-0.28.0.dist-info/AUTHORS
pymod2pkg-0.28.0.dist-info/LICENSE
pymod2pkg-0.28.0.dist-info/METADATA
pymod2pkg-0.28.0.dist-info/WHEEL
pymod2pkg-0.28.0.dist-info/entry_points.txt
pymod2pkg-0.28.0.dist-info/pbr.json
pymod2pkg-0.28.0.dist-info/top_level.txt
pymod2pkg-0.28.0.dist-info/RECORD
