Metadata-Version: 2.1
Name: pymod2pkg
Version: 0.28.0
Summary: python module name to package name map
Home-page: https://docs.openstack.org/pymod2pkg/latest/
Author: OpenStack
Author-email: openstack-discuss@lists.openstack.org
License: UNKNOWN
Platform: UNKNOWN
Classifier: Programming Language :: Python :: 3
Classifier: Programming Language :: Python :: 3.6
Classifier: Programming Language :: Python :: 3.7
Classifier: Programming Language :: Python :: 3.8
Classifier: Intended Audience :: Developers
Classifier: License :: OSI Approved :: Apache Software License
Classifier: Topic :: Software Development :: Libraries
Classifier: Topic :: Utilities
Requires-Python: >=3.6
Requires-Dist: distro
Requires-Dist: packaging
Requires-Dist: pbr (!=2.1.0,>=2.0.0)
